dummynames/__init__.py
dummynames/adjs
dummynames/namegen.py
dummynames/names
dummynames-1.0.dist-info/METADATA
dummynames-1.0.dist-info/RECORD
dummynames-1.0.dist-info/WHEEL
dummynames-1.0.dist-info/top_level.txt
