Metadata-Version: 2.1
Name: dummynames
Version: 1.0
Summary: Generate random non-existent name. (First Name + Adjective)
Home-page: UNKNOWN
Author: Kirill Matsaberydze
Author-email: UNKNOWN
License: UNKNOWN
Platform: UNKNOWN
